udpipe_parser/__init__.py
udpipe_parser/dicts.py
udpipe_parser/text_preprocessor.py
udpipe_parser/udpipe_parser.py
udpipe_parser/utilities.py
udpipe_parser_test-2.4.dist-info/METADATA
udpipe_parser_test-2.4.dist-info/WHEEL
udpipe_parser_test-2.4.dist-info/top_level.txt
udpipe_parser_test-2.4.dist-info/RECORD
