Metadata-Version: 2.1
Name: udpipe-parser-test
Version: 2.4
Summary: UDPipe-based Parser brings Universal Dependencies trees in more practical form.
Home-page: https://github.com/constantin50/udpipe_parser
Author: Constantin Werner
Author-email: const.werner@gmail.com
License: MIT
Keywords: parser,Universal Dependencies,NLP,russian,syntax
Platform: UNKNOWN
Classifier: Programming Language :: Python :: 3
Classifier: License :: OSI Approved :: MIT License
Classifier: Operating System :: OS Independent
Requires-Dist: morpholog
Requires-Dist: conllu
Requires-Dist: separatrice
Requires-Dist: nltk
